delitoolkit/__init__.py
delitoolkit/deliannotate.py
delitoolkit/delidata.py
delitoolkit/delitoolkit.py
delitoolkit/encoding_utils.py
delitoolkit/delidata_corpus/00639b9b-3a45-4c59-90f6-a4738de92fd4
delitoolkit/delidata_corpus/0128a2aa-53a2-4874-8bfe-b71ce287e7c2
delitoolkit/delidata_corpus/01acf3e3-714c-4d53-9b74-9170a645bcd0
delitoolkit/delidata_corpus/01e7d47c-8831-4492-abb0-88f94c7b02a3
delitoolkit/delidata_corpus/02972b77-c909-499e-8d4b-8920a25707f0
delitoolkit/delidata_corpus/03714d9c-9c47-4103-9b61-ed51c76e1ef6
delitoolkit/delidata_corpus/038c3e5e-35bf-4e26-b96d-8ff92bb8c830
delitoolkit/delidata_corpus/04edccd6-25d7-47dc-b73f-5bce9d77025b
delitoolkit/delidata_corpus/05627bda-cc61-43bb-833f-90e6140074dc
delitoolkit/delidata_corpus/05b01d11-9edb-41b7-a330-cf21fa421183
delitoolkit/delidata_corpus/0610068a-0d3d-4fc2-a81b-94a74454700a
delitoolkit/delidata_corpus/0686b2d0-dddc-4052-92b2-2c274f3e4def
delitoolkit/delidata_corpus/069dce94-a359-41a6-afb5-d9d074c7fcc3
delitoolkit/delidata_corpus/06d658f6-d0ad-4fef-9a1c-6353b9700f18
delitoolkit/delidata_corpus/07160ace-1991-462a-a52e-81fb44a6c59a
delitoolkit/delidata_corpus/071d0952-edd7-4fed-9d76-6add6632e68e
delitoolkit/delidata_corpus/074de597-b9e9-4186-ae35-261cc8ef46f7
delitoolkit/delidata_corpus/083f6017-4c39-43be-8687-31f5a901717b
delitoolkit/delidata_corpus/0884e8f0-ca8f-413a-9455-f166a0ad67d8
delitoolkit/delidata_corpus/08c890ac-c67f-4be7-aaba-8c3f31c8abc1
delitoolkit/delidata_corpus/08f1f827-f181-403b-9e1d-0843a43e8a65
delitoolkit/delidata_corpus/09b321d6-e6b9-446a-96af-79d89d66d71d
delitoolkit/delidata_corpus/0a057d01-a7d0-4028-9daf-c71751339d16
delitoolkit/delidata_corpus/0aeeb8d8-c358-46c5-a181-5d4f0b6f1d95
delitoolkit/delidata_corpus/0b1354b8-4d4b-4b50-ab1e-3d1e7d9ac780
delitoolkit/delidata_corpus/0b37e6fb-eb3b-4c65-a886-2f9be44d5380
delitoolkit/delidata_corpus/0b8fe30f-2304-48aa-a3ed-f80e45ea9024
delitoolkit/delidata_corpus/0cac5462-55f1-4a16-954c-0e7351652e53
delitoolkit-0.3.9.dist-info/AUTHORS.rst
delitoolkit-0.3.9.dist-info/LICENSE
delitoolkit-0.3.9.dist-info/METADATA
delitoolkit-0.3.9.dist-info/WHEEL
delitoolkit-0.3.9.dist-info/top_level.txt
delitoolkit-0.3.9.dist-info/RECORD
