Metadata-Version: 2.1
Name: delitoolkit
Version: 0.3.9
Summary: A toolkit for evaluating deliberative discussions and building DEliBots. For more details see delibot.xyz
Home-page: https://github.com/gkaradzhov/delitoolkit
Author: Georgi Karadzhov
Author-email: georgi.m.karadjov@gmail.com
License: Apache Software License 2.0
Keywords: delitoolkit
Classifier: Development Status :: 2 - Pre-Alpha
Classifier: Intended Audience :: Developers
Classifier: License :: OSI Approved :: Apache Software License
Classifier: Natural Language :: English
Classifier: Programming Language :: Python :: 3
Classifier: Programming Language :: Python :: 3.6
Classifier: Programming Language :: Python :: 3.7
Classifier: Programming Language :: Python :: 3.8
Requires-Python: >=3.6
License-File: LICENSE
License-File: AUTHORS.rst
Requires-Dist: sentence-transformers >=2.2.2
Requires-Dist: torch >=2.1.2
Requires-Dist: transformers >=4.20.1
Requires-Dist: numpy >=1.24.4
Requires-Dist: scikit-learn ==1.2.2
